{
	"webapps":{
		"title":"Webapps",
		"action":"list",
		"urls":[{
			"name":"Inventory",
			"href":"/pages/inventory/",
			"type":"link"
		},{
			"name":"MLT",
			"href":"/pages/mlt/",
			"type":"link"
		},{
			"name":"TBOC",
			"href":"/pages/tboc/",
			"type":"link"
		},{
			"name":"Codefront",
			"href":"/pages/codefront/",
			"type":"link"
		},{
			"name":"Jmac217.net",
			"href":"/pages/jmac217.net/",
			"type":"link"
		},{
			"name":"CustomersDB",
			"href":"/pages/customer/",
			"type":"link"
		},{
			"name":"FJC-IL",
			"href":"/pages/fjc-il_rework/",
			"type":"link"
		}]
	},
	"modules":{
		"title":"Modules",
		"action":"list",
		"urls":[{
			"name":"Queued",
			"href":"landing/php/queued/",
			"type":"link"
		},{
			"name":"Jot",
			"href":"landing/php/jot/",
			"type":"link"
		},{
			"name":"Lucent",
			"href":"landing/php/lucent/",
			"type":"link"		
		},{
			"name":"Bugger",
			"href":"landing/php/bugger/",
			"type":"link"
		}]
	},
	"scripts":{
		"title":"Scripts",
		"action":"self",
		"urls":[{
			"name":"",
			"href":"",
			"type":""
		}]
	},
	"databases":{
		"title":"Databases",
		"action":"inline",
		"urls":[{
			"name":"Localhost",
			"href":"http://localhost/phpmyadmin",
			"type":"link"
		},{
			"name":"Ubuntu",
			"href":"ubuntu/phpmyadmin",
			"type":"link"
		},{
			"name":"GoDaddy",
			"href":"godaddy/phpmyadmin",
			"type":"link"
		}]
	}
}
